cherrypy_foundation/__init__.py
cherrypy_foundation/error_page.py
cherrypy_foundation/flash.py
cherrypy_foundation/form.py
cherrypy_foundation/logging.py
cherrypy_foundation/passwd.py
cherrypy_foundation/sessions.py
cherrypy_foundation/url.py
cherrypy_foundation/widgets.py
cherrypy_foundation/components/ColorModes.jinja
cherrypy_foundation/components/Datatable.css
cherrypy_foundation/components/Datatable.jinja
cherrypy_foundation/components/Datatable.js
cherrypy_foundation/components/Field.css
cherrypy_foundation/components/Field.jinja
cherrypy_foundation/components/Field.js
cherrypy_foundation/components/Fields.jinja
cherrypy_foundation/components/Flash.jinja
cherrypy_foundation/components/Icon.jinja
cherrypy_foundation/components/LocaleSelection.jinja
cherrypy_foundation/components/LocaleSelection.js
cherrypy_foundation/components/SideBySideMultiSelect.css
cherrypy_foundation/components/SideBySideMultiSelect.jinja
cherrypy_foundation/components/SideBySideMultiSelect.js
cherrypy_foundation/components/Typeahead.css
cherrypy_foundation/components/Typeahead.jinja
cherrypy_foundation/components/Typeahead.js
cherrypy_foundation/components/__init__.py
cherrypy_foundation/components/tests/__init__.py
cherrypy_foundation/components/tests/test_static.py
cherrypy_foundation/components/vendor/bootstrap-icons/bootstrap-icons.css
cherrypy_foundation/components/vendor/bootstrap-icons/bootstrap-icons.min.css
cherrypy_foundation/components/vendor/bootstrap-icons/fonts/bootstrap-icons.woff
cherrypy_foundation/components/vendor/bootstrap-icons/fonts/bootstrap-icons.woff2
cherrypy_foundation/components/vendor/bootstrap5/css/bootstrap.css
cherrypy_foundation/components/vendor/bootstrap5/css/bootstrap.css.map
cherrypy_foundation/components/vendor/bootstrap5/css/bootstrap.min.css
cherrypy_foundation/components/vendor/bootstrap5/css/bootstrap.min.css.map
cherrypy_foundation/components/vendor/bootstrap5/js/bootstrap.js
cherrypy_foundation/components/vendor/bootstrap5/js/bootstrap.js.map
cherrypy_foundation-1.0.0a21.dist-info/licenses/LICENSE.md
cherrypy_foundation-1.0.0a21.dist-info/METADATA
cherrypy_foundation-1.0.0a21.dist-info/WHEEL
cherrypy_foundation-1.0.0a21.dist-info/top_level.txt
cherrypy_foundation-1.0.0a21.dist-info/RECORD
