Metadata-Version: 2.4
Name: cherrypy-foundation
Version: 1.0.0a21
Summary: Cherrypy-foundation
Author-email: Patrik Dufresne <patrik@ikus-soft.com>
License: GPLv3
Project-URL: Homepage, https://gitlab.com/ikus-soft/cherrypy-foundation
Classifier: Development Status :: 4 - Beta
Classifier: Framework :: CherryPy
Classifier: Intended Audience :: System Administrators
Classifier: Programming Language :: Python :: 3.11
Classifier: Programming Language :: Python :: 3.12
Classifier: Programming Language :: Python :: 3.13
Requires-Python: <4,>=3.11
License-File: LICENSE.md
Requires-Dist: babel
Requires-Dist: CherryPy
Requires-Dist: Jinja2
Requires-Dist: jinjax
Requires-Dist: pytz
Requires-Dist: WTForms>=3.2.1
Provides-Extra: test
Requires-Dist: apscheduler; extra == "test"
Requires-Dist: argon2-cffi; extra == "test"
Requires-Dist: ldap3; extra == "test"
Requires-Dist: parameterized; extra == "test"
Requires-Dist: pytest; extra == "test"
Requires-Dist: requests_oauthlib; extra == "test"
Requires-Dist: selenium; extra == "test"
Requires-Dist: sqlalchemy; extra == "test"
Provides-Extra: ldap
Requires-Dist: ldap3; extra == "ldap"
Provides-Extra: oauth
Requires-Dist: requests_oauthlib; extra == "oauth"
Provides-Extra: passwd
Requires-Dist: argon2-cffi; extra == "passwd"
Provides-Extra: scheduler
Requires-Dist: apscheduler; extra == "scheduler"
Dynamic: license-file
